{"file":"jdm-trading-DlYnILrz.js","mappings":";;;;;;;;;;;;;;;;;AAAuD,MAAe,aAAA,gBAAgB,uBAAuB;ACAtD,MAAe,aAAA,gBAAgB,yBAAyB;;;;;ACC/G,UAAM,YAAY,IAAI,EAAE;AACxB,UAAM,cAAc,IAAI,EAAE;AAE1B,UAAM,SAAS,iBAAgB;AAE/B,aAAS,QAAQ,GAAG,QAAQ,GAAG,SAAS;AACpC,gBAAU,MAAM,KAAK;AAAA,QACjB,KAAK,GAAG,OAAO,IAAI,OAAO,cAAc,KAAK;AAAA,MACrD,CAAK;AAAA,IACL;AAEA,aAAS,QAAQ,GAAG,QAAQ,GAAG,SAAS;AACpC,kBAAY,MAAM,KAAK;AAAA,QACnB,KAAK,GAAG,OAAO,IAAI,OAAO,cAAc,KAAK;AAAA,MACrD,CAAK;AAAA,IACL;;;;;;;;;;;;;;;;;","names":[],"sources":["../../../../virtual:public?%2Fvideos%2Fjdm-panel.mp4","../../../../virtual:public?%2Fvideos%2Fjdm-website.mp4","../../../../pages/projects/jdm-trading.vue"],"sourcesContent":["import { publicAssetsURL } from '#internal/nuxt/paths';export default publicAssetsURL(\"/videos/jdm-panel.mp4\")","import { publicAssetsURL } from '#internal/nuxt/paths';export default publicAssetsURL(\"/videos/jdm-website.mp4\")","<script setup>\r\nconst webImages = ref([])\r\nconst panelImages = ref([])\r\n\r\nconst config = useRuntimeConfig();\r\n\r\nfor (let index = 0; index < 4; index++) {\r\n    webImages.value.push({\r\n        src: `${config.app.baseURL}images/jdm-${index}.png`\r\n    })\r\n}\r\n\r\nfor (let index = 4; index < 9; index++) {\r\n    panelImages.value.push({\r\n        src: `${config.app.baseURL}images/jdm-${index}.png`\r\n    })\r\n}\r\n</script>\r\n<template>\r\n\r\n    <div class=\"container\">\r\n        <div class=\"project\">\r\n            <div class=\"row\">\r\n                <div class=\"col-md-6\">\r\n                    <h2>JDM Trading - Car Stock Management Website</h2>\r\n                    <p><strong>Live Link</strong>: <a href=\"https://jdm-trading.com/\" target=\"_blank\">JDM Trading</a>\r\n                    </p>\r\n                    <p><strong>Technologies Used</strong>: Laravel, jQuery, Bootstrap 5</p>\r\n\r\n                    <h3>Project Overview</h3>\r\n                    <p>\r\n                        Developed <strong>JDM Trading</strong>, a car stock management website where users can view all\r\n                        available car stock with labels indicating whether the cars are reserved or available for sale.\r\n                        The\r\n                        website includes essential pages like <strong>Home</strong>, <strong>About</strong>,\r\n                        <strong>Stock\r\n                            List</strong>, and <strong>Contact</strong>. The <strong>admin panel</strong> allows\r\n                        administrators\r\n                        to manage stock category-wise, track expenses, manage sales, handle CNF (Cost and Freight), and\r\n                        update\r\n                        dynamic content for the website.\r\n                    </p>\r\n\r\n\r\n                </div>\r\n                <div class=\"col-md-6\">\r\n                    <h4>Website</h4>\r\n                    <video src=\"/videos/jdm-panel.mp4\" type=\"video/mp4\" controls width=\"100%\"> </video>\r\n                    <GalleryImages :images=\"webImages\" />\r\n\r\n\r\n\r\n\r\n                </div>\r\n            </div>\r\n\r\n            <div class=\"row\">\r\n                <div class=\"col-md-6\">\r\n                    <div>\r\n                        <h4 class=\"mt-3\">Admin Panel</h4>\r\n                        <video src=\"/videos/jdm-website.mp4\" type=\"video/mp4\" controls width=\"100%\"> </video>\r\n                        <GalleryImages :images=\"panelImages\" />\r\n                    </div>\r\n\r\n                </div>\r\n\r\n                <div class=\"col-md-6\">\r\n                    <div class=\"p-3 bg-black mt-3\">\r\n                        <h3>Key Features and Modules</h3>\r\n                        <ol>\r\n                            <li>\r\n                                <strong>Website Features</strong>:\r\n                                <ul>\r\n                                    <li><strong>Home Page</strong>: Displays featured car stock and highlights.</li>\r\n                                    <li><strong>About Page</strong>: Provides information about the company and\r\n                                        services.\r\n                                    </li>\r\n                                    <li><strong>Stock List Page</strong>: Lists all available car stock with filters and\r\n                                        search\r\n                                        functionality.</li>\r\n                                    <ul>\r\n                                        <li>Each car listing includes details like make, model, year, price, and\r\n                                            availability status\r\n                                            (e.g., \"Available\" or \"Reserved\").</li>\r\n                                    </ul>\r\n                                    <li><strong>Contact Page</strong>: Allows users to send inquiries or messages to the\r\n                                        company.\r\n                                    </li>\r\n                                </ul>\r\n                            </li>\r\n                            <li>\r\n                                <strong>Admin Panel Features</strong>:\r\n                                <ul>\r\n                                    <li><strong>Stock Management</strong>: Add, update, or remove car listings\r\n                                        category-wise.</li>\r\n                                    <li><strong>Expense Management</strong>: Track and manage expenses related to car\r\n                                        stock.\r\n                                    </li>\r\n                                    <li><strong>Sales Management</strong>: Manage sales records and update sales status.\r\n                                    </li>\r\n                                    <li><strong>CNF Management</strong>: Handle Cost and Freight details for each car.\r\n                                    </li>\r\n                                    <li><strong>Dynamic Content Management</strong>: Update website content (e.g.,\r\n                                        banners,\r\n                                        text,\r\n                                        images) from the admin panel.</li>\r\n                                    <li><strong>Settings</strong>: Configure website settings and preferences.</li>\r\n                                </ul>\r\n                            </li>\r\n                        </ol>\r\n                    </div>\r\n                </div>\r\n            </div>\r\n\r\n\r\n\r\n            <h3>My Role and Contributions</h3>\r\n            <ul>\r\n                <li>Developed the <strong>frontend website</strong> using <strong>Bootstrap 5</strong> and\r\n                    <strong>jQuery</strong> for a responsive and user-friendly interface.\r\n                </li>\r\n                <li>Built the <strong>admin panel</strong> using <strong>Laravel</strong> for managing car stock,\r\n                    expenses, sales, CNF, and dynamic content.</li>\r\n                <li>Implemented search and filter functionality for the <strong>Stock List Page</strong>.</li>\r\n                <li>Designed and developed the <strong>contact form</strong> and inquiry management system.</li>\r\n                <li>Ensured the website was optimized for performance and scalability.</li>\r\n            </ul>\r\n\r\n            <h3>Technologies Used</h3>\r\n            <ul>\r\n                <li><strong>Frontend</strong>: Bootstrap 5, jQuery</li>\r\n                <li><strong>Backend</strong>: Laravel, RESTful APIs</li>\r\n                <li><strong>Database</strong>: MySQL</li>\r\n                <li><strong>Version Control</strong>: Git</li>\r\n            </ul>\r\n\r\n        </div>\r\n    </div>\r\n\r\n\r\n</template>"],"version":3}